pca_inputter/__init__.py
pca_inputter/pca_inputter.py
pca_inputter-0.1.3.dist-info/LICENSE.txt
pca_inputter-0.1.3.dist-info/METADATA
pca_inputter-0.1.3.dist-info/WHEEL
pca_inputter-0.1.3.dist-info/top_level.txt
pca_inputter-0.1.3.dist-info/RECORD
