Metadata-Version: 2.1
Name: pca-inputter
Version: 0.1.3
Summary: Package for handling missing values in numerical datasets
Home-page: https://github.com/maleckicoa/pca_inputter/
Author: Aleksa Mihajlovic
Author-email: mihajlovic.aleksa@gmail.com
License: LICENSE.txt
Requires-Python: >=3.7.1
License-File: LICENSE.txt
Requires-Dist: pandas >=1.3.5
Requires-Dist: numpy >=1.17.3
Requires-Dist: scikit-learn >=0.22.2
